skyline/__init__.py
skyline/skyline.py
skyline.py-0.0.5.dist-info/LICENSE
skyline.py-0.0.5.dist-info/METADATA
skyline.py-0.0.5.dist-info/WHEEL
skyline.py-0.0.5.dist-info/top_level.txt
skyline.py-0.0.5.dist-info/RECORD
