Metadata-Version: 2.1
Name: skyline.py
Version: 0.0.5
Summary: Interacts with the Skyline Bots API
Home-page: UNKNOWN
Author: Yoshiboi18303 (Brice Coley)
Author-email: <yoshiboi18303.t@gmail.com>
License: UNKNOWN
Keywords: python,skyline,spyapi,skyline api,api,skyline bots
Platform: UNKNOWN
Classifier: Development Status :: 2 - Pre-Alpha
Classifier: Intended Audience :: Developers
Classifier: Programming Language :: Python :: 3
Classifier: Operating System :: Unix
Classifier: Operating System :: MacOS :: MacOS X
Classifier: Operating System :: Microsoft :: Windows
Classifier: License :: OSI Approved :: MIT License
Classifier: Natural Language :: English
Requires-Dist: aiohttp (>=3.7.4)
